{
    "relevance": 0.5302700904481619,
    "id": "29746977",
    "external_id": "46-202100-2932-831549",
    "original_id": null,
    "label": "[]",
    "webpage_url": "https://arbetsformedlingen.se/platsbanken/annonser/29746977",
    "logo_url": "https://arbetsformedlingen.se/rest/agas/api/v1/organisation/2021002932/logotyper/logo.png",
    "headline": "Doktorand i självkörande kemilaboratorier för CO₂-konvertering",
    "application_deadline": "2025-07-01T23:59:59",
    "number_of_vacancies": 1,
    "description": {
        "text": "Institutionen för kemi - Ångström bedriver forskning och utbildning inom kemiämnet.\r\n\r\nInstitutionen har 270 anställda och omsätter 300 miljoner kronor. Vid institutionens sex program bedrivs mycket framgångsrik forskning av hög internationell klass. Vi har ett stort antal externt finansierade forskningsprojekt, ofta med internationellt samarbete och vi ser en fortsatt god tillväxt inom vårt ämnesområde. Institutionen har utbildningsuppdrag inom ingenjörs- och civilingenjörsprogram samt masterprogram. Mer information finns på vår https://www.uu.se/institution/kemi-angstrom. https://www.uu.se/institution/kemi-angstrom\n\nProjektbeskrivning \nAtt omvandla CO₂ till fler-kolprodukter genom elektrokatalys är en attraktiv strategi för att både minska utsläppen av växthusgaser och lagra överskottsenergi från förnybara källor i kemisk form. Trots att framsteg inom katalysatordesign har förbättrat den selektiva bildningen av fler-kolprodukter avsevärt, är påverkan från reaktionsmiljön, såsom pH, joner och deras koncentrationer, på produktselektionen fortfarande otillräckligt utforskad. Detta projekt syftar till att utveckla ett självstyrande laboratorium för autonom formulering och utvärdering av elektrolyter, vilket möjliggör snabb kartläggning av katalysatorselektion i relation till reaktionsmiljön under CO₂-reduktion (CO₂RR). Det övergripande målet är att bygga en grundläggande mekanistisk förståelse för hur miljöfaktorer påverkar selektiviteten mot fler-kolprodukter vid elektrokemisk CO₂-konvertering genom ett datadrivet experimentellt tillvägagångssätt.\n\nArbetsuppgifter \nDoktoranden förväntas:\n\n - Utveckla och optimera ett självstyrande laboratorium för CO₂RR, inklusive automatisering av elektrolytformulering och provtagning av produkter.\n - Planera och utföra analyser av CO₂-reduktionskatalysatorer med elektrokemiska metoder.\n - Analysera data med avancerade databehandlingstekniker, inklusive maskininlärning och statistiska metoder för tolkning.\n - Presentera forskningsresultat vid gruppmöten, internationella konferenser och i vetenskapligt granskade publikationer.\n - Genomföra forskarutbildningskurser relevanta för doktorandutbildningen.\n\nArbetsuppgifterna kan även omfatta undervisning och andra institutionella uppdrag, dock högst 20 % av arbetstiden.\n\nKvalifikationskrav \nDen sökande ska ha:\n\n - avlagt examen på avancerad nivå eller\n - fullgjort kursfordringar om minst 240 högskolepoäng, varav minst 60 högskolepoäng på avancerad nivå (varav 15 högskolepoäng utgör självständigt arbete), med innehåll som är relevant för forskarutbildningen eller \n - på något annat sätt inom eller utom landet förvärvat i huvudsak motsvarande kunskaper\n - mycket goda kunskaper i engelska, i tal och skrift.\n - examen på avancerad nivå eller motsvarande enligt ovan inom elektrokemi, fysikalisk kemi eller ett relaterat område.\n\nStor vikt kommer också att läggas vid personliga egenskaper såsom god samarbetsförmåga, driv och självständighet samt hur den sökande genom sin erfarenhet och kompetens bedöms ha den förmåga som behövs för att klara forskarutbildningen.\n\nÖnskvärt/meriterande i övrigt\nPraktisk erfarenhet av elektrokatalys och experimentell automation är meriterande. Färdigheter i Python betraktas som en merit.\n\nOm anställningen \nAnställningen är tidsbegränsad, enligt HF 5 kap § 7. Omfattningen är heltid. Tillträde 2025-09-01 eller enligt överenskommelse. Placeringsort: Kemi Ångström, Uppsala\n\nBestämmelser för doktorander återfinns i Högskoleförordningen 5 kap §§ 1-7 samt i https://www.uu.se/medarbetare/organisation-styrning/regler/\n\nUpplysningar om anställningen lämnas av: Alina Sekretareva, alina.sekretareva@kemi.uu.se\n\n\nVälkommen med din ansökan senast den 1 juli 2025, UFV-PA 2025/1769.\n\nUppsala universitet är ett brett forskningsuniversitet med stark internationell ställning. Det yttersta målet är att bedriva utbildning och forskning av högsta kvalitet och relevans för att göra skillnad i samhället. Vår viktigaste tillgång är alla 7 600 anställda och 53 000 studenter som med nyfikenhet och engagemang gör Uppsala universitet till en av landets mest spännande arbetsplatser.\n\n\nLäs mer om våra förmåner och hur det är att jobba inom Uppsala universitet\nhttps://uu.se/om-uu/jobba-hos-oss/\n\n\nAnställningen kan komma att säkerhetsprövas. Vid säkerhetsprövning är en förutsättning för anställning att sökande blir godkänd.\n\n\nVi undanber oss erbjudanden om rekryterings- och annonseringshjälp.\n\n\nAnsökan tas emot i Uppsala universitets rekryteringssystem.",
        "text_formatted": "Institutionen för kemi - Ångström bedriver forskning och utbildning inom kemiämnet.\r\n\r\nInstitutionen har 270 anställda och omsätter 300 miljoner kronor. Vid institutionens sex program bedrivs mycket framgångsrik forskning av hög internationell klass. Vi har ett stort antal externt finansierade forskningsprojekt, ofta med internationellt samarbete och vi ser en fortsatt god tillväxt inom vårt ämnesområde. Institutionen har utbildningsuppdrag inom ingenjörs- och civilingenjörsprogram samt masterprogram. Mer information finns på vår https://www.uu.se/institution/kemi-angstrom. https://www.uu.se/institution/kemi-angstrom\n\nProjektbeskrivning \nAtt omvandla CO₂ till fler-kolprodukter genom elektrokatalys är en attraktiv strategi för att både minska utsläppen av växthusgaser och lagra överskottsenergi från förnybara källor i kemisk form. Trots att framsteg inom katalysatordesign har förbättrat den selektiva bildningen av fler-kolprodukter avsevärt, är påverkan från reaktionsmiljön, såsom pH, joner och deras koncentrationer, på produktselektionen fortfarande otillräckligt utforskad. Detta projekt syftar till att utveckla ett självstyrande laboratorium för autonom formulering och utvärdering av elektrolyter, vilket möjliggör snabb kartläggning av katalysatorselektion i relation till reaktionsmiljön under CO₂-reduktion (CO₂RR). Det övergripande målet är att bygga en grundläggande mekanistisk förståelse för hur miljöfaktorer påverkar selektiviteten mot fler-kolprodukter vid elektrokemisk CO₂-konvertering genom ett datadrivet experimentellt tillvägagångssätt.\n\nArbetsuppgifter \nDoktoranden förväntas:\n\n - Utveckla och optimera ett självstyrande laboratorium för CO₂RR, inklusive automatisering av elektrolytformulering och provtagning av produkter.\n - Planera och utföra analyser av CO₂-reduktionskatalysatorer med elektrokemiska metoder.\n - Analysera data med avancerade databehandlingstekniker, inklusive maskininlärning och statistiska metoder för tolkning.\n - Presentera forskningsresultat vid gruppmöten, internationella konferenser och i vetenskapligt granskade publikationer.\n - Genomföra forskarutbildningskurser relevanta för doktorandutbildningen.\n\nArbetsuppgifterna kan även omfatta undervisning och andra institutionella uppdrag, dock högst 20 % av arbetstiden.\n\nKvalifikationskrav \nDen sökande ska ha:\n\n - avlagt examen på avancerad nivå eller\n - fullgjort kursfordringar om minst 240 högskolepoäng, varav minst 60 högskolepoäng på avancerad nivå (varav 15 högskolepoäng utgör självständigt arbete), med innehåll som är relevant för forskarutbildningen eller \n - på något annat sätt inom eller utom landet förvärvat i huvudsak motsvarande kunskaper\n - mycket goda kunskaper i engelska, i tal och skrift.\n - examen på avancerad nivå eller motsvarande enligt ovan inom elektrokemi, fysikalisk kemi eller ett relaterat område.\n\nStor vikt kommer också att läggas vid personliga egenskaper såsom god samarbetsförmåga, driv och självständighet samt hur den sökande genom sin erfarenhet och kompetens bedöms ha den förmåga som behövs för att klara forskarutbildningen.\n\nÖnskvärt/meriterande i övrigt\nPraktisk erfarenhet av elektrokatalys och experimentell automation är meriterande. Färdigheter i Python betraktas som en merit.\n\nOm anställningen \nAnställningen är tidsbegränsad, enligt HF 5 kap § 7. Omfattningen är heltid. Tillträde 2025-09-01 eller enligt överenskommelse. Placeringsort: Kemi Ångström, Uppsala\n\nBestämmelser för doktorander återfinns i Högskoleförordningen 5 kap §§ 1-7 samt i https://www.uu.se/medarbetare/organisation-styrning/regler/\n\nUpplysningar om anställningen lämnas av: Alina Sekretareva, alina.sekretareva@kemi.uu.se\n\n\nVälkommen med din ansökan senast den 1 juli 2025, UFV-PA 2025/1769.\n\nUppsala universitet är ett brett forskningsuniversitet med stark internationell ställning. Det yttersta målet är att bedriva utbildning och forskning av högsta kvalitet och relevans för att göra skillnad i samhället. Vår viktigaste tillgång är alla 7 600 anställda och 53 000 studenter som med nyfikenhet och engagemang gör Uppsala universitet till en av landets mest spännande arbetsplatser.\n\n\nLäs mer om våra förmåner och hur det är att jobba inom Uppsala universitet\nhttps://uu.se/om-uu/jobba-hos-oss/\n\n\nAnställningen kan komma att säkerhetsprövas. Vid säkerhetsprövning är en förutsättning för anställning att sökande blir godkänd.\n\n\nVi undanber oss erbjudanden om rekryterings- och annonseringshjälp.\n\n\nAnsökan tas emot i Uppsala universitets rekryteringssystem.",
        "company_information": null,
        "needs": null,
        "requirements": null,
        "conditions": "100. Tillträde: 2025-09-01 eller enligt överenskommelse\r\nVisstidsanställning till "
    },
    "employment_type": {
        "concept_id": "PFZr_Syz_cUq",
        "label": "Vanlig anställning",
        "legacy_ams_taxonomy_id": "1"
    },
    "salary_type": {
        "concept_id": "oG8G_9cW_nRf",
        "label": "Fast månads- vecko- eller timlön",
        "legacy_ams_taxonomy_id": "1"
    },
    "salary_description": "Fast lön",
    "duration": {
        "concept_id": "qQUd_4qe_NDT",
        "label": "6 månader eller längre",
        "legacy_ams_taxonomy_id": "2"
    },
    "working_hours_type": {
        "concept_id": "6YE1_gAC_R2G",
        "label": "Heltid",
        "legacy_ams_taxonomy_id": "1"
    },
    "scope_of_work": {
        "min": 100,
        "max": 100
    },
    "access": null,
    "employer": {
        "phone_number": null,
        "email": null,
        "url": null,
        "organization_number": "2021002932",
        "name": "Uppsala Universitet",
        "workplace": "Uppsala universitet, Institutionen för kemi - Ångström"
    },
    "application_details": {
        "information": null,
        "reference": "UFV-PA 2025/1769",
        "email": null,
        "via_af": false,
        "url": "https://uu.varbi.com/what:job/jobID:831549/type:job/where:1/apply:1",
        "other": null
    },
    "experience_required": true,
    "access_to_own_car": false,
    "driving_license_required": false,
    "driving_license": null,
    "occupation": {
        "concept_id": "HtLv_4EJ_o5r",
        "label": "Kemist",
        "legacy_ams_taxonomy_id": "5764"
    },
    "occupation_group": {
        "concept_id": "eofS_oZs_RZi",
        "label": "Kemister",
        "legacy_ams_taxonomy_id": "2113"
    },
    "occupation_field": {
        "concept_id": "kJeN_wmw_9wX",
        "label": "Naturvetenskap",
        "legacy_ams_taxonomy_id": "14"
    },
    "workplace_address": {
        "municipality": "Uppsala",
        "municipality_code": "0380",
        "municipality_concept_id": "otaF_bQY_4ZD",
        "region": "Uppsala län",
        "region_code": "03",
        "region_concept_id": "zBon_eET_fFU",
        "country": "Sverige",
        "country_code": "199",
        "country_concept_id": "i46j_HmG_v64",
        "street_address": null,
        "postcode": null,
        "city": null,
        "coordinates": [
            17.638927,
            59.858562
        ]
    },
    "must_have": {
        "skills": [],
        "languages": [],
        "work_experiences": [
            {
                "weight": 10,
                "concept_id": "HtLv_4EJ_o5r",
                "label": "Kemist",
                "legacy_ams_taxonomy_id": "5764"
            }
        ],
        "education": [],
        "education_level": []
    },
    "nice_to_have": {
        "skills": [],
        "languages": [],
        "work_experiences": [],
        "education": [],
        "education_level": []
    },
    "application_contacts": [],
    "publication_date": "2025-06-03T11:19:53",
    "last_publication_date": "2025-07-01T23:59:59",
    "removed": false,
    "removed_date": null,
    "source_type": "VIA_PLATSBANKEN_DXA",
    "timestamp": 1748942393292
}